Metadata-Version: 2.1
Name: gces-subsfm
Version: 0.0.1a0
Summary: GCES Subscriber Framework
Home-page: UNKNOWN
Author: Daniel Debonzi
Author-email: debonzi@gmail.com
License: UNKNOWN
Keywords: pubsub gces google
Platform: UNKNOWN
Classifier: Programming Language :: Python
Classifier: License :: OSI Approved :: GNU Library or Lesser General Public License (LGPL)
Classifier: Development Status :: 3 - Alpha
Classifier: Intended Audience :: Developers
Classifier: Topic :: Software Development :: Libraries :: Python Modules
Classifier: Programming Language :: Python :: 2.7
Classifier: Programming Language :: Python :: 3.5
Classifier: Programming Language :: Python :: 3.6
Provides-Extra: test
Provides-Extra: ci
